setup.py
ici/__init__.py
ici/ici.py
ici.egg-info/PKG-INFO
ici.egg-info/SOURCES.txt
ici.egg-info/dependency_links.txt
ici.egg-info/entry_points.txt
ici.egg-info/not-zip-safe
ici.egg-info/requires.txt
ici.egg-info/top_level.txt