Metadata-Version: 1.0
Name: ici
Version: 0.4
Summary: 方便程序员在terminal查询生词的小工具
Home-page: http://lazynight.me
Author: yuzhe
Author-email: lazynightz@gmail.com
License: UNKNOWN
Keywords: python iciba dictionary terminal
Platform: UNKNOWN
